psi4_help/__init__.py
psi4_help/__main__.py
psi4_help/main.py
psi4_help/psi4_help.py
psi4_help/psi4_keywords.yaml
psi4_help-0.1.0.dist-info/LICENSE
psi4_help-0.1.0.dist-info/METADATA
psi4_help-0.1.0.dist-info/WHEEL
psi4_help-0.1.0.dist-info/entry_points.txt
psi4_help-0.1.0.dist-info/top_level.txt
psi4_help-0.1.0.dist-info/RECORD
