Metadata-Version: 2.1
Name: psi4-help
Version: 0.1.0
Summary: A helper script for Psi4 keywords
Home-page: https://github.com/FLongWang/psi4-help
Author: F.L. Wang
Author-email: FL058@foxmail.com
Classifier: Programming Language :: Python :: 3
Classifier: License :: OSI Approved :: MIT License
Classifier: Operating System :: OS Independent
Requires-Python: >=3
License-File: LICENSE
Requires-Dist: PyYAML
Requires-Dist: colorama
